Metadata-Version: 1.0
Name: aq-udacity-distribution
Version: 0.1
Summary: Gaussian & Binomial Distributions
Home-page: UNKNOWN
Author: UNKNOWN
Author-email: UNKNOWN
License: UNKNOWN
Platform: UNKNOWN
